dev_quick_init/__init__.py
dev_quick_init/installer.py
dev_quick_init/samples.py
dev_quick_init-0.1.9.dist-info/licenses/LICENSE
dev_quick_init-0.1.9.dist-info/METADATA
dev_quick_init-0.1.9.dist-info/WHEEL
dev_quick_init-0.1.9.dist-info/entry_points.txt
dev_quick_init-0.1.9.dist-info/top_level.txt
dev_quick_init-0.1.9.dist-info/RECORD
