Metadata-Version: 2.4
Name: dev-quick-init
Version: 0.1.9
Summary: Quick developer machine setup from YAML
Author-email: Stephen Krol <you@example.com>
License: MIT
Project-URL: homepage, https://github.com/stivio00/dev-quick-init
Project-URL: repository, https://github.com/stivio00/dev-quick-init
Requires-Python: >=3.10
License-File: LICENSE
Requires-Dist: pyyaml
Requires-Dist: click
Dynamic: license-file
